MANIFEST.in
README.md
setup.py
analysis/CCC_model.py
analysis/Cell_model.py
analysis/Gene_model.py
analysis/Image_cell_segmentation.py
analysis/Preprocess_Cell_module.py
analysis/Preprocess_Gene_module.py
analysis/Processing.R
stKeep/Layers.py
stKeep/__init__.py
stKeep/image_processing.py
stKeep/model_training.py
stKeep/modules.py
stKeep/utilities.py
stKeep.egg-info/PKG-INFO
stKeep.egg-info/SOURCES.txt
stKeep.egg-info/dependency_links.txt
stKeep.egg-info/requires.txt
stKeep.egg-info/top_level.txt