Metadata-Version: 2.1
Name: stKeep
Version: 0.0.21
Summary: stKeep for processing spatially transcriptomics data
Home-page: https://github.com/cmzuo11/stKeep
Author: cmzuo
Author-email: cmzuo@dhu.edu.cn
License: MIT License
Keywords: TME
Platform: any
Requires-Dist: numpy==1.22.4
Requires-Dist: pandas==2.0.3
Requires-Dist: scipy==1.8.1
Requires-Dist: scikit-learn
Requires-Dist: torch==1.13.0
Requires-Dist: tqdm==4.51.0
Requires-Dist: scanpy==1.9.6
Requires-Dist: seaborn
Requires-Dist: matplotlib==3.7.3
Requires-Dist: glob2
Requires-Dist: Pillow==9.5.0
Requires-Dist: anndata==0.9.2
Requires-Dist: argparse==1.1
Requires-Dist: pathlib
Requires-Dist: opencv-python==4.8.1.78
Requires-Dist: torchvision==0.14.0
